norsulabs/__init__.py
norsulabs/client.py
norsulabs-0.0.3.dist-info/licenses/LICENSE
norsulabs-0.0.3.dist-info/METADATA
norsulabs-0.0.3.dist-info/WHEEL
norsulabs-0.0.3.dist-info/top_level.txt
norsulabs-0.0.3.dist-info/RECORD
