Metadata-Version: 2.4
Name: norsulabs
Version: 0.0.3
Summary: Python client for NorsuLabs API
Requires-Python: >=3.11
License-File: LICENSE
Requires-Dist: requests>=2.32.4
Dynamic: license-file
